dataprepkit/__init__.py
dataprepkit/data_prep_kit.py
tests/__init__.py
tests/test_dataprepkit.py
dataprepkit_ao-1.0.0.dist-info/METADATA
dataprepkit_ao-1.0.0.dist-info/WHEEL
dataprepkit_ao-1.0.0.dist-info/top_level.txt
dataprepkit_ao-1.0.0.dist-info/RECORD
