Metadata-Version: 2.1
Name: dataprepkit-ao
Version: 1.0.0
Summary: A streamlined data preprocessing toolkit for machine learning
Home-page: https://github.com/yourusername/dataprepkit-ao
Author: Abdalrahman Osama
Author-email: abdalrahman.osama01@gmail.com
Classifier: Programming Language :: Python :: 3
Classifier: License :: OSI Approved :: MIT License
Classifier: Operating System :: OS Independent
Requires-Python: >=3.6
Requires-Dist: pandas
Requires-Dist: numpy
Requires-Dist: scikit-learn
